<?xml version='1.1' encoding='UTF-8'?>
<com.cloudbees.plugins.credentials.SystemCredentialsProvider plugin="credentials@2.3.14">
  <domainCredentialsMap class="hudson.util.CopyOnWriteMap$Hash">
    <entry>
      <com.cloudbees.plugins.credentials.domains.Domain>
        <specifications/>
      </com.cloudbees.plugins.credentials.domains.Domain>
      <java.util.concurrent.CopyOnWriteArrayList>
        <com.cloudbees.plugins.credentials.impl.UsernamePasswordCredentialsImpl>
          <scope>GLOBAL</scope>
          <id>17a93426-0189-45d4-8bf0-2adcfaa1ad3a</id>
          <description></description>
          <username>remote_user</username>
          <password>{AQAAABAAAAAQIgp9xe7mu/wnz79PeF4iwUf3fq7kpEGvHiL+xH6Fulo=}</password>
        </com.cloudbees.plugins.credentials.impl.UsernamePasswordCredentialsImpl>
        <org.jenkinsci.plugins.plaincredentials.impl.StringCredentialsImpl plugin="plain-credentials@1.7">
          <scope>GLOBAL</scope>
          <id>MYSQL_PASSWORD</id>
          <description></description>
          <secret>{AQAAABAAAAAQfA4Ew+4NSNvZmvevViI1sYcYbB9R2VFftE68y+V8Ruw=}</secret>
        </org.jenkinsci.plugins.plaincredentials.impl.StringCredentialsImpl>
        <org.jenkinsci.plugins.plaincredentials.impl.StringCredentialsImpl plugin="plain-credentials@1.7">
          <scope>GLOBAL</scope>
          <id>AWS_SECRET</id>
          <description></description>
          <secret>{AQAAABAAAAAw5VTGMpEcUo6lS2VTZLmuRgkqyUiua8QkOfqvu3pL1Ta2XOEOnMBkWEGC70p3298MhhdP+Y70ir8H6HxV3WSNUw==}</secret>
        </org.jenkinsci.plugins.plaincredentials.impl.StringCredentialsImpl>
      </java.util.concurrent.CopyOnWriteArrayList>
    </entry>
  </domainCredentialsMap>
</com.cloudbees.plugins.credentials.SystemCredentialsProvider>